orats/__init__.py
orats/api/__init__.py
orats/api/data.py
orats/main.py
orats/model/__init__.py
orats/model/core.py
orats/model/money.py
orats/model/response.py
orats/model/strike.py
orats/model/summary.py
orats/model/underlying.py
orats/model/volatility.py
orats/py.typed
orats/utility.py
orats-0.1.1a0.dist-info/LICENSE
orats-0.1.1a0.dist-info/WHEEL
orats-0.1.1a0.dist-info/METADATA
orats-0.1.1a0.dist-info/RECORD
